{
  "posts": [
    {
      "title": "ㅋㅋㅋ 졸려워요",
      "content": "너무 졸립죠? 네?",
      "createdAt": 1742300413866,
      "id": 10
    },
    {
      "title": "테스트 입니다!! @@",
      "content": "새로 등록을 합시다 ? ! ㅋㅋㅋ",
      "createdAt": 1742822636267,
      "id": 11
    },
    {
      "title": "하하 안녕하세요!!",
      "content": "하하 안녕하세요 반갑?!",
      "createdAt": 1742823030588,
      "id": 12
    },
    {
      "title": "안녕하세요!!",
      "content": "반갑습니다 ㅎㅎ @@ 반갑습니다 ㅎㅎ @@ \n반갑습니다 ㅎㅎ @@ \n반갑습니다 ㅎㅎ @@ \n반갑습니다 ㅎㅎ @@ \n반갑습니다 ㅎㅎ @@ \n반갑습니다 ㅎㅎ @@ \n\n반갑습니다 ㅎㅎ @@ \n반갑습니다 ㅎㅎ @@ \n",
      "id": 13
    }
  ]
}